{
  "Categories": [
    {
      "Name": "???",
      "ETAs": [
        {
          "CreationOrder": 2,
          "Name": "Maniacal Magnitudes",
          "RunState": "Running",
          "Goal": 60000,
          "EtaData": {
            "Goal": 60000,
            "Data": [
              {
                "Value": 12332,
                "Date": "2025-07-29T13:45:16.6161703-07:00"
              },
              {
                "Value": 13846,
                "Date": "2025-07-30T20:18:58.812533-07:00"
              },
              {
                "Value": 13919,
                "Date": "2025-07-31T08:10:15.9691428-07:00"
              },
              {
                "Value": 14423,
                "Date": "2025-07-31T13:16:03.2598792-07:00"
              },
              {
                "Value": 14582,
                "Date": "2025-07-31T15:34:32.6183406-07:00"
              },
              {
                "Value": 15140,
                "Date": "2025-07-31T17:16:29.9056476-07:00"
              },
              {
                "Value": 15365,
                "Date": "2025-07-31T18:55:14.6496818-07:00"
              }
            ]
          }
        },
        {
          "CreationOrder": 3,
          "Name": "XP",
          "RunState": "Running",
          "Goal": 100,
          "EtaData": {
            "Goal": 100,
            "Data": [
              {
                "Value": 1,
                "Date": "2025-07-30T19:45:33.3945628-07:00"
              },
              {
                "Value": 17,
                "Date": "2025-07-31T08:10:20.6411256-07:00"
              },
              {
                "Value": 36,
                "Date": "2025-07-31T13:43:11.8630353-07:00"
              },
              {
                "Value": 25,
                "Date": "2025-07-31T17:16:15.3777878-07:00"
              },
              {
                "Value": 29,
                "Date": "2025-07-31T18:23:22.8013913-07:00"
              },
              {
                "Value": 31,
                "Date": "2025-07-31T18:39:07.133995-07:00"
              },
              {
                "Value": 37,
                "Date": "2025-07-31T18:55:21.5774332-07:00"
              }
            ]
          }
        }
      ]
    },
    {
      "Name": "???",
      "ETAs": [
        {
          "CreationOrder": 4,
          "Name": "Niko",
          "RunState": "Running",
          "Goal": 30,
          "EtaData": {
            "Goal": 30,
            "Data": [
              {
                "Value": 4,
                "Date": "2025-07-30T21:52:20.6826-07:00"
              },
              {
                "Value": 5,
                "Date": "2025-07-31T19:41:10.9265379-07:00"
              }
            ]
          }
        },
        {
          "CreationOrder": 5,
          "Name": "Einhar",
          "RunState": "Running",
          "Goal": 30,
          "EtaData": {
            "Goal": 30,
            "Data": [
              {
                "Value": 4,
                "Date": "2025-07-30T21:52:30.7627751-07:00"
              },
              {
                "Value": 5,
                "Date": "2025-07-31T08:57:25.670641-07:00"
              },
              {
                "Value": 8,
                "Date": "2025-07-31T12:22:41.1127743-07:00"
              },
              {
                "Value": 12,
                "Date": "2025-07-31T15:33:35.8184517-07:00"
              },
              {
                "Value": 13,
                "Date": "2025-07-31T17:16:42.9616394-07:00"
              },
              {
                "Value": 15,
                "Date": "2025-07-31T18:55:33.8816311-07:00"
              },
              {
                "Value": 17,
                "Date": "2025-07-31T19:41:14.9265271-07:00"
              }
            ]
          }
        },
        {
          "CreationOrder": 6,
          "Name": "Jun",
          "RunState": "Running",
          "Goal": 30,
          "EtaData": {
            "Goal": 30,
            "Data": [
              {
                "Value": 1,
                "Date": "2025-07-30T21:52:39.4985063-07:00"
              }
            ]
          }
        },
        {
          "CreationOrder": 7,
          "Name": "Alva",
          "RunState": "Running",
          "Goal": 30,
          "EtaData": {
            "Goal": 30,
            "Data": [
              {
                "Value": 5,
                "Date": "2025-07-30T21:52:50.8264867-07:00"
              },
              {
                "Value": 6,
                "Date": "2025-07-31T08:56:48.2459814-07:00"
              },
              {
                "Value": 9,
                "Date": "2025-07-31T12:22:44.3610419-07:00"
              },
              {
                "Value": 13,
                "Date": "2025-07-31T15:33:41.0344587-07:00"
              },
              {
                "Value": 14,
                "Date": "2025-07-31T17:16:46.4495268-07:00"
              },
              {
                "Value": 16,
                "Date": "2025-07-31T18:55:37.5135025-07:00"
              },
              {
                "Value": 18,
                "Date": "2025-07-31T19:41:19.8226793-07:00"
              }
            ]
          }
        }
      ]
    }
  ]
}